fbscrape/__init__.py
fbscrape/fbscrape.py
fbscrape-0.0.4.dist-info/LICENSE.txt
fbscrape-0.0.4.dist-info/METADATA
fbscrape-0.0.4.dist-info/WHEEL
fbscrape-0.0.4.dist-info/top_level.txt
fbscrape-0.0.4.dist-info/RECORD
