Metadata-Version: 2.1
Name: fbscrape
Version: 0.0.4
Summary: A package to scrape the likes of a facebook page and its posts
Home-page: https://github.com/ted-marozzi/facebook-likes-scrape
Author: Edward Marozzi
Author-email: marozzi.t@gmail.com
License: UNKNOWN
Platform: UNKNOWN
Classifier: Programming Language :: Python :: 3
Classifier: License :: OSI Approved :: MIT License
Classifier: Operating System :: OS Independent
Requires-Python: >=3.6
